pyeqx/azure/__init__.py
pyeqx/azure/constants.py
pyeqx/azure/errors.py
pyeqx/azure/helper.py
pyeqx/core/__init__.py
pyeqx/core/common.py
pyeqx/core/configuration.py
pyeqx/core/constants.py
pyeqx/core/errors.py
pyeqx/core/main.py
pyeqx/core/operation.py
pyeqx/core/reader.py
pyeqx/core/retry.py
pyeqx/core/schemas.py
pyeqx/core/writer.py
pyeqx/execution/__init__.py
pyeqx/execution/parameter.py
pyeqx/execution/process.py
pyeqx/execution/process_base.py
pyeqx-0.7.17.dist-info/METADATA
pyeqx-0.7.17.dist-info/WHEEL
pyeqx-0.7.17.dist-info/top_level.txt
pyeqx-0.7.17.dist-info/RECORD
