Metadata-Version: 2.4
Name: pyeqx
Version: 0.7.17
Summary: Python library for interacting with Spark, Azure, Minio, and other data sources.
Author: ESBM Cronus
Classifier: Programming Language :: Python :: 3
Requires-Python: >=3.11
Requires-Dist: adlfs>=2024.2.0
Requires-Dist: azure-identity>=1.13.0
Requires-Dist: azure-storage-blob>=12.16.0
Requires-Dist: azure-storage-file-datalake>=12.11.0
Requires-Dist: azure-storage-queue>=12.6.0
Requires-Dist: delta-spark<3.3.0,>=3.2.0
Requires-Dist: minio>=7.2.3
Requires-Dist: numpy>=1.26.0
Requires-Dist: pandas>=2.2.0
Requires-Dist: psycopg2-binary>=2.9.9
Requires-Dist: pymssql>=2.2.11
Requires-Dist: pyspark>=3.5.3
Requires-Dist: requests>=2.30.0
Requires-Dist: tenacity>=8.2.1
Requires-Dist: pyeqx-common>=0.1.0
Provides-Extra: dev
Requires-Dist: black; extra == "dev"
Requires-Dist: ruff; extra == "dev"
Requires-Dist: build; extra == "dev"
Requires-Dist: twine; extra == "dev"
Requires-Dist: python-dotenv; extra == "dev"
Requires-Dist: pytest; extra == "dev"
Requires-Dist: pytest-cov; extra == "dev"
Requires-Dist: pytest-mock; extra == "dev"
Requires-Dist: pytest-watch; extra == "dev"
